scierror/__init__.py
scierror/main.py
scierror-0.0.3.dist-info/LICENSE
scierror-0.0.3.dist-info/METADATA
scierror-0.0.3.dist-info/WHEEL
scierror-0.0.3.dist-info/top_level.txt
scierror-0.0.3.dist-info/RECORD
