Metadata-Version: 2.1
Name: scierror
Version: 0.0.3
Summary: Laboratory report tools in Python.
Home-page: https://github.com/segFault15/scierror
Author: segFault15
License: UNKNOWN
Platform: UNKNOWN
Classifier: Programming Language :: Python :: 3
Classifier: Intended Audience :: Science/Research
Classifier: License :: OSI Approved :: MIT License
Requires-Dist: matplotlib
Requires-Dist: numpy
